nat/meta/pypi.md
nat/plugins/ragaai/__init__.py
nat/plugins/ragaai/ragaai_catalyst_exporter.py
nat/plugins/ragaai/register.py
nat/plugins/ragaai/mixin/__init__.py
nat/plugins/ragaai/mixin/ragaai_catalyst_mixin.py
nvidia_nat_ragaai-1.3.1.dist-info/licenses/LICENSE-3rd-party.txt
nvidia_nat_ragaai-1.3.1.dist-info/licenses/LICENSE.md
nvidia_nat_ragaai-1.3.1.dist-info/METADATA
nvidia_nat_ragaai-1.3.1.dist-info/WHEEL
nvidia_nat_ragaai-1.3.1.dist-info/entry_points.txt
nvidia_nat_ragaai-1.3.1.dist-info/top_level.txt
nvidia_nat_ragaai-1.3.1.dist-info/RECORD
